Metadata-Version: 2.1
Name: pyfusekiutil
Version: 0.1.9
Summary: Manage a Fuseki-Triple Store
Home-page: https://github.com/bartoc-basel/fuseki-update
Author: Jonas Waeber
License: UNKNOWN
Keywords: fuseki triple-store skos skosmos skosify
Platform: UNKNOWN
Classifier: Development Status :: 3 - Alpha
Classifier: Intended Audience :: Developers
Classifier: Programming Language :: Python :: 3.6
